{
    "citation": "Kerry D. Woods. 2009. Multi-decade, spatially explicit population studies of canopy dynamics in Michigan old-growth forests. Ecology 90:3587.",
    "description": "The data set provides stem infomation from a regular grid of 256 permanent plots includes about 20% of a 100-ha old-growth forest at the Dukes Research Natural Area in northern Michigan, USA.",
    "homepage": "https://figshare.com/collections/Multi-decade_spatially_explicit_population_studies_of_canopy_dynamics_in_Michigan_old-growth_forests/3301757",
    "keywords": [
        "plants",
        "local-scale",
        "time-series",
        "observational"
    ],
    "name": "forest-plots-michigan",
    "resources": [
        {
            "dialect": {
                "missingValues": [
                    "NA"
                ]
            },
            "name": "all_plots_1935_1948",
            "schema": {},
            "url": "https://ndownloader.figshare.com/files/5608016"
        },
        {
            "dialect": {
                "missingValues": [
                    "NA"
                ]
            },
            "name": "all_plots_1974_1980",
            "schema": {},
            "url": "https://ndownloader.figshare.com/files/5608019"
        },
        {
            "dialect": {},
            "name": "swamp",
            "schema": {},
            "url": "https://ndownloader.figshare.com/files/5608025"
        },
        {
            "dialect": {},
            "name": "species_codes",
            "schema": {},
            "url": "https://ndownloader.figshare.com/files/5608028"
        },
        {
            "dialect": {
                "missingValues": [
                    "NA",
                    ""
                ]
            },
            "name": "upland_plots_1989_2007",
            "schema": {},
            "url": "https://ndownloader.figshare.com/files/5608022"
        },
        {
            "dialect": {
                "missingValues": [
                    "NA"
                ]
            },
            "name": "sampling_history",
            "schema": {
                "fields": [
                    {
                        "name": "record_id",
                        "type": "pk-auto"
                    },
                    {
                        "name": "plot",
                        "size": "10",
                        "type": "char"
                    },
                    {
                        "name": "yr_1935",
                        "size": "10",
                        "type": "char"
                    },
                    {
                        "name": "yr_1948",
                        "size": "10",
                        "type": "char"
                    },
                    {
                        "name": "yr_1974",
                        "size": "10",
                        "type": "char"
                    },
                    {
                        "name": "yr_1978",
                        "size": "10",
                        "type": "char"
                    },
                    {
                        "name": "yr_1979",
                        "size": "10",
                        "type": "char"
                    },
                    {
                        "name": "yr_1989",
                        "size": "10",
                        "type": "char"
                    },
                    {
                        "name": "yr_1992",
                        "size": "10",
                        "type": "char"
                    },
                    {
                        "name": "yr_1993",
                        "size": "10",
                        "type": "char"
                    },
                    {
                        "name": "yr_1994",
                        "size": "10",
                        "type": "char"
                    },
                    {
                        "name": "yr_1997",
                        "size": "10",
                        "type": "char"
                    },
                    {
                        "name": "yr_1999",
                        "size": "10",
                        "type": "char"
                    },
                    {
                        "name": "yr_2001",
                        "size": "10",
                        "type": "char"
                    },
                    {
                        "name": "yr_2002",
                        "size": "10",
                        "type": "char"
                    },
                    {
                        "name": "yr_2004",
                        "size": "10",
                        "type": "char"
                    },
                    {
                        "name": "yr_2007",
                        "size": "10",
                        "type": "char"
                    }
                ]
            },
            "url": "https://ndownloader.figshare.com/files/5608031"
        }
    ],
    "retriever": "True",
    "retriever_minimum_version": "2.0.dev",
    "title": "Michigan forest canopy dynamics plots - Woods et al. 2009",
    "urls": {
        "all_plots_1935_1948": "https://ndownloader.figshare.com/files/5608016",
        "all_plots_1974_1980": "https://ndownloader.figshare.com/files/5608019",
        "sampling_history": "https://ndownloader.figshare.com/files/5608031",
        "species_codes": "https://ndownloader.figshare.com/files/5608028",
        "swamp": "https://ndownloader.figshare.com/files/5608025",
        "upland_plots_1989_2007": "https://ndownloader.figshare.com/files/5608022"
    },
    "version": "1.2.0"
}
